zentorch/_C.cpython-313-x86_64-linux-gnu.so
zentorch/_StaticQuantizedLinear.py
zentorch/_WOQLinear.py
zentorch/_WOQ_embedding_bag.py
zentorch/__init__.py
zentorch/_build_info.py
zentorch/_compile_backend.py
zentorch/_custom_op_replacement.py
zentorch/_eltwise_binary_fusions.py
zentorch/_eltwise_unary_fusions.py
zentorch/_freeze_utils.py
zentorch/_freezing.py
zentorch/_fusion_matcher.py
zentorch/_fusion_patterns.py
zentorch/_graph_cleanup.py
zentorch/_graph_preprocess_matcher.py
zentorch/_graph_preprocess_patterns.py
zentorch/_info.py
zentorch/_logging.py
zentorch/_meta_registrations.py
zentorch/_mkldnn.py
zentorch/_op_replacement.py
zentorch/_optimize.py
zentorch/_qop_replacement.py
zentorch/_quant_model_reload.py
zentorch/_quantization_utils.py
zentorch/_utils.py
zentorch/libzentorch.so
zentorch/utils.py
zentorch/llm/__init__.py
zentorch/llm/_checks.py
zentorch/llm/_custom_model_forward.py
zentorch/llm/_custom_models_reference_linear_fusion.py
zentorch/llm/_model_conversion_functions.py
zentorch/llm/_optimize.py
zentorch/vllm/__init__.py
zentorch/vllm/platform.py
zentorch/vllm/runner.py
zentorch/vllm/zentorch_attention.py
zentorch/vllm/zentorch_worker.py
zentorch-5.1.0.dist-info/LICENCE
zentorch-5.1.0.dist-info/METADATA
zentorch-5.1.0.dist-info/WHEEL
zentorch-5.1.0.dist-info/entry_points.txt
zentorch-5.1.0.dist-info/top_level.txt
zentorch-5.1.0.dist-info/RECORD
