Metadata-Version: 2.2
Name: zentorch
Version: 5.1.0
Summary: zentorch : A PyTorch* extension for AMD EPYC CPUs.
Home-page: https://developer.amd.com/zendnn
Author: AMD
Author-email: zendnn.maintainers@amd.com
License: MIT
Keywords: pytorch tensor machine learning plugin ZenDNN AMD
License-File: LICENCE
Requires-Dist: numpy
Requires-Dist: torch
Requires-Dist: deprecated
Requires-Dist: safetensors
Provides-Extra: llm
Requires-Dist: intel_extension_for_pytorch~=2.7.0; extra == "llm"
Dynamic: author
Dynamic: author-email
Dynamic: description
Dynamic: description-content-type
Dynamic: home-page
Dynamic: keywords
Dynamic: license
Dynamic: provides-extra
Dynamic: requires-dist
Dynamic: summary
